pyshex/__init__.py
pyshex/evaluate.py
pyshex/git_describe.txt
pyshex/prefixlib.py
pyshex/shex_evaluator.py
pyshex/user_agent.py
pyshex/parse_tree/__init__.py
pyshex/parse_tree/parse_node.py
pyshex/shape_expressions_language/__init__.py
pyshex/shape_expressions_language/p3_terminology.py
pyshex/shape_expressions_language/p5_2_validation_definition.py
pyshex/shape_expressions_language/p5_3_shape_expressions.py
pyshex/shape_expressions_language/p5_4_node_constraints.py
pyshex/shape_expressions_language/p5_5_shapes_and_triple_expressions.py
pyshex/shape_expressions_language/p5_6_schema_requirements.py
pyshex/shape_expressions_language/p5_7_semantic_actions.py
pyshex/shape_expressions_language/p5_context.py
pyshex/shapemap_structure_and_language/__init__.py
pyshex/shapemap_structure_and_language/p1_notation_and_terminology.py
pyshex/shapemap_structure_and_language/p3_shapemap_structure.py
pyshex/shapemap_structure_and_language/p4_shapemap_usage.py
pyshex/shex_manifest/__init__.py
pyshex/shex_manifest/manifest.py
pyshex/sparql11_query/__init__.py
pyshex/sparql11_query/p17_1_operand_data_types.py
pyshex/utils/__init__.py
pyshex/utils/collection_utils.py
pyshex/utils/datatype_utils.py
pyshex/utils/deprecated.py
pyshex/utils/matchesEachOfEvaluator.py
pyshex/utils/n3_mapper.py
pyshex/utils/partitions.py
pyshex/utils/rdf_namespace.py
pyshex/utils/schema_loader.py
pyshex/utils/schema_utils.py
pyshex/utils/slurp_utils.py
pyshex/utils/sparql_query.py
pyshex/utils/stringtoken.py
pyshex/utils/tortoise.py
pyshex/utils/trace_utils.py
pyshex/utils/url_utils.py
pyshex/utils/value_set_utils.py
PyShEx-0.8.1.dist-info/AUTHORS
PyShEx-0.8.1.dist-info/METADATA
PyShEx-0.8.1.dist-info/WHEEL
PyShEx-0.8.1.dist-info/entry_points.txt
PyShEx-0.8.1.dist-info/pbr.json
PyShEx-0.8.1.dist-info/top_level.txt
PyShEx-0.8.1.dist-info/RECORD
